{"stats":{"minecraft:mined":{"minecraft:dark_oak_planks":14,"minecraft:white_bed":4,"quark:diorite_bricks":1,"minecraft:jungle_leaves":89,"minecraft:obsidian":5,"minecraft:acacia_log":22,"minecraft:jungle_log":76,"quark:magma_bricks":11,"minecraft:oak_pressure_plate":1,"minecraft:coal_block":1,"minecraft:magma_block":54,"minecraft:fire":61,"minecraft:pumpkin":8,"minecraft:enchanting_table":1,"byg:embur_sprouts":1,"quark:limestone":4,"minecraft:tripwire":3,"minecraft:brown_mushroom":6,"byg:soapstone_pillar":1,"minecraft:smoker":2,"minecraft:torch":37,"minecraft:melon":28,"minecraft:glass":11,"minecraft:sugar_cane":24,"byg:magmatic_stone":12,"minecraft:chain":6,"byg:soapstone":269,"minecraft:repeater":5,"minecraft:wheat":278,"minecraft:black_bed":5,"minecraft:stone_brick_stairs":6,"minecraft:grass":787,"quark:stone_vertical_slab":17,"minecraft:stonecutter":12,"minecraft:mossy_cobblestone":7,"quark:jungle_trapped_chest":1,"minecraft:spruce_fence":3,"minecraft:jungle_planks":57,"minecraft:redstone_wire":17,"minecraft:kelp":2,"minecraft:redstone_ore":31,"minecraft:snow":22,"minecraft:andesite":88,"minecraft:diamond_block":1,"minecraft:cobblestone_slab":8,"minecraft:vine":20,"byg:rocky_stone":225,"minecraft:bamboo":6,"minecraft:smithing_table":2,"minecraft:redstone_block":3,"minecraft:glass_pane":2,"quark:oak_chest":3,"quark:dark_oak_chest":2,"minecraft:dandelion":1,"quark:cobblestone_bricks_vertical_slab":22,"quark:netherrack_bricks":28,"minecraft:campfire":1,"minecraft:tall_grass":5,"minecraft:diorite":3,"minecraft:coarse_dirt":1,"byg:scoria_stone":98,"minecraft:cobblestone_wall":11,"minecraft:spruce_log":32,"minecraft:jungle_fence":29,"quark:white_candle":10,"byg:pine_log":163,"pamhc2crops:frostgarden":4,"byg:soapstone_tile":12,"byg:embur_gel_block":1,"minecraft:gravel":597,"minecraft:cobweb":3,"minecraft:stone_bricks":11,"minecraft:gold_ore":35,"minecraft:fern":63,"quark:root":1,"minecraft:stone_pressure_plate":6,"minecraft:spruce_planks":1,"quark:magma_bricks_stairs":3,"minecraft:jungle_slab":2,"minecraft:cobblestone_stairs":12,"minecraft:spruce_trapdoor":1,"minecraft:grass_block":1099,"quark:cobblestone_bricks_wall":3,"minecraft:polished_diorite":2,"byg:tall_embur_roots":3,"minecraft:composter":4,"byg:polished_soapstone":1,"minecraft:iron_ore":333,"minecraft:dark_oak_stairs":1,"minecraft:skeleton_wall_skull":1,"minecraft:iron_bars":7,"minecraft:spruce_slab":1,"quark:dirt_bricks":4,"quark:cobblestone_bricks_stairs":30,"minecraft:soul_lantern":1,"minecraft:clay":158,"quark:cobblestone_bricks":41,"minecraft:poppy":5,"quark:stone_speleothem":3,"minecraft:chest":2,"quark:jungle_bookshelf":9,"byg:firecracker_flower_bush":2,"minecraft:cobblestone":185,"minecraft:grindstone":1,"minecraft:oak_planks":27,"minecraft:wall_torch":34,"minecraft:seagrass":6,"minecraft:dark_oak_slab":5,"pamhc2crops:aridgarden":1,"minecraft:light_gray_wool":2,"minecraft:oak_log":17,"minecraft:beetroots":4,"minecraft:lime_terracotta":5,"minecraft:sand":282,"minecraft:dirt":599,"minecraft:dispenser":1,"minecraft:oak_leaves":1339,"minecraft:emerald_block":1,"byg:scoria_cobblestone":3,"minecraft:oak_door":1,"quark:framed_glass":4,"minecraft:lever":6,"quark:netherrack_bricks_stairs":4,"minecraft:spruce_leaves":122,"quark:jasper":2,"minecraft:large_fern":2,"minecraft:hay_block":23,"minecraft:furnace":2,"minecraft:gold_block":1,"minecraft:bookshelf":17,"minecraft:stone":2821,"byg:araucaria_leaves":121,"minecraft:acacia_leaves":7,"minecraft:scaffolding":63,"pamhc2crops:windygarden":6,"pamhc2trees:pampaperbark":4,"minecraft:spruce_door":3,"minecraft:crafting_table":3,"minecraft:andesite_slab":1,"minecraft:lectern":2,"quark:lime_framed_glass":19,"pamhc2crops:pamwintersquashcrop":1,"quark:cobblestone_bricks_slab":58,"minecraft:lapis_ore":7,"minecraft:spruce_stairs":1,"minecraft:cactus":1,"quark:shallow_dirt":1,"minecraft:ice":11,"byg:short_grass":38,"minecraft:grass_path":4,"pamhc2crops:soggygarden":12,"minecraft:coal_ore":562,"quark:oak_hedge":1,"minecraft:cocoa":3},"minecraft:picked_up":{"pamhc2crops:wintersquashitem":8,"minecraft:smithing_table":2,"minecraft:lead":34,"pamhc2crops:broccoliitem":1,"minecraft:golden_sword":3,"minecraft:music_disc_cat":5,"minecraft:string":20,"minecraft:cooked_salmon":39,"byg:pine_log":146,"byg:soapstone_pillar":1,"minecraft:beetroot":4,"minecraft:gold_nugget":20,"minecraft:spruce_planks":2,"pamhc2trees:candlenutitem":20,"pamhc2foodextended:bamboosteamedriceitem":19,"quark:root_item":5,"minecraft:melon_slice":50,"minecraft:coal_block":1,"artifacts:universal_attractor":1,"minecraft:composter":2,"minecraft:acacia_log":21,"quark:red_rune":1,"quark:clear_shard":15,"minecraft:iron_bars":8,"minecraft:snowball":19,"minecraft:magma_block":54,"minecraft:feather":16,"minecraft:jungle_log":95,"minecraft:smoker":2,"artifacts:thorn_pendant":1,"minecraft:flint":65,"pamhc2trees:cherryitem":22,"pamhc2trees:mangoitem":17,"minecraft:stonecutter":12,"byg:araucaria_sapling":10,"quark:cobblestone_bricks_slab":57,"minecraft:lime_terracotta":5,"minecraft:ink_sac":19,"quark:cobblestone_bricks_wall":3,"quark:jasper":1,"minecraft:dispenser":1,"minecraft:lever":6,"minecraft:golden_horse_armor":1,"byg:pine_planks":36,"minecraft:diamond_pickaxe":2,"minecraft:coarse_dirt":1,"pamhc2trees:vanillabeanitem":8,"minecraft:crafting_table":3,"minecraft:clay_ball":332,"quark:dark_oak_chest":2,"pamhc2trees:starfruititem":5,"minecraft:snow":1,"minecraft:beef":19,"quark:magma_bricks_stairs":3,"minecraft:poppy":5,"minecraft:iron_nugget":1,"minecraft:jungle_sapling":10,"minecraft:spruce_slab":1,"minecraft:minecart":1,"minecraft:chest":2,"pamhc2foodextended:chocolatecoconutbaritem":1,"minecraft:egg":165,"minecraft:stone":93,"minecraft:oak_door":1,"pamhc2crops:celeryitem":1,"minecraft:spruce_fence":3,"pamhc2foodcore:skilletitem":1,"quark:jungle_chest":4,"minecraft:carrot":28,"minecraft:redstone":221,"minecraft:tnt":1,"minecraft:cooked_cod":1,"minecraft:beetroot_seeds":9,"minecraft:hay_block":23,"pamhc2crops:brusselsproutitem":3,"quark:framed_glass":19,"quark:jungle_bookshelf":17,"minecraft:rail":2,"minecraft:white_wool":57,"quark:dirt_bricks":4,"minecraft:fern":1,"minecraft:jungle_fence":43,"minecraft:oak_log":14,"pamhc2trees:soursopitem":5,"quark:limestone":4,"minecraft:paper":49,"minecraft:white_banner":1,"pamhc2trees:plumitem":9,"pamhc2foodcore:friesitem":1,"minecraft:apple":18,"minecraft:stone_bricks":11,"minecraft:stone_pickaxe":1,"minecraft:iron_ore":336,"minecraft:cobweb":3,"pamhc2crops:asparagusitem":1,"minecraft:iron_sword":1,"minecraft:dark_oak_stairs":1,"pamhc2crops:greengrapeitem":5,"endrem:old_pearl":1,"minecraft:dark_oak_slab":5,"minecraft:sweet_berries":2,"minecraft:gravel":615,"pamhc2crops:okraitem":3,"minecraft:spruce_sapling":4,"endrem:end_castle_disc":2,"minecraft:spruce_log":31,"quark:cobblestone_bricks":56,"travelersbackpack:standard":1,"minecraft:polished_diorite":2,"quark:oak_hedge":1,"minecraft:painting":23,"quark:netherrack_bricks_stairs":4,"pamhc2crops:tomatilloitem":7,"minecraft:melon_seeds":2,"pamhc2trees:coconutitem":15,"quark:stone_speleothem":10,"minecraft:wheat":779,"pamhc2crops:elderberryitem":1,"travelersbackpack:bat":2,"minecraft:redstone_block":3,"minecraft:stone_brick_stairs":6,"pamhc2trees:avocadoitem":12,"minecraft:zombie_head":2,"minecraft:bucket":1,"minecraft:cobblestone_slab":8,"minecraft:furnace":2,"minecraft:stick":47,"quark:jungle_trapped_chest":1,"minecraft:torch":187,"minecraft:spruce_stairs":1,"minecraft:porkchop":5,"minecraft:music_disc_pigstep":3,"minecraft:diorite":3,"minecraft:vine":6,"minecraft:cactus":5,"minecraft:rotten_flesh":91,"minecraft:music_disc_ward":2,"pamhc2crops:quinoaitem":1,"byg:embur_gel_ball":4,"minecraft:obsidian":4,"minecraft:cod":1,"minecraft:cobblestone":3587,"minecraft:enchanting_table":1,"byg:polished_soapstone":1,"minecraft:magma_cream":5,"minecraft:repeater":5,"minecraft:andesite":88,"minecraft:black_bed":4,"minecraft:golden_leggings":1,"minecraft:potato":3,"pamhc2crops:caulifloweritem":1,"minecraft:lapis_lazuli":54,"minecraft:dirt":991,"minecraft:glass":6,"minecraft:bone":18,"minecraft:bow":1,"pamhc2trees:tamarinditem":2,"minecraft:wheat_seeds":1681,"pamhc2crops:riceitem":20,"minecraft:grindstone":2,"minecraft:bamboo":71,"byg:tall_embur_roots":2,"minecraft:oak_planks":24,"minecraft:ghast_tear":2,"minecraft:oak_pressure_plate":1,"minecraft:jungle_planks":80,"minecraft:sand":256,"minecraft:melon":21,"minecraft:grass_block":554,"quark:lime_framed_glass":19,"minecraft:diamond_block":1,"byg:magmatic_stone":12,"minecraft:mossy_cobblestone":7,"minecraft:jungle_leaves":1,"quark:cobblestone_bricks_stairs":29,"minecraft:clay":74,"minecraft:soul_lantern":1,"quark:magma_bricks":11,"minecraft:crossbow":3,"pamhc2crops:waterchestnutitem":2,"minecraft:bone_meal":4,"minecraft:grass":5,"minecraft:emerald":84,"minecraft:oak_sapling":66,"minecraft:netherrack":20,"minecraft:oak_leaves":204,"minecraft:andesite_slab":1,"pamhc2trees:pampaperbark":3,"minecraft:cocoa_beans":13,"minecraft:charcoal":2,"quark:stone_vertical_slab":18,"byg:soapstone":458,"minecraft:chicken":14,"minecraft:brown_mushroom":6,"pamhc2crops:amaranthitem":1,"minecraft:gold_block":1,"minecraft:chain":6,"minecraft:shield":1,"quark:cobblestone_bricks_vertical_slab":23,"minecraft:iron_axe":1,"pamhc2trees:dragonfruititem":2,"minecraft:sugar_cane":47,"minecraft:light_gray_wool":2,"minecraft:lectern":2,"minecraft:spruce_trapdoor":1,"minecraft:phantom_membrane":2,"pamhc2trees:pistachioitem":1,"pamhc2trees:figitem":8,"pamhc2trees:pearitem":1,"pamhc2trees:orangeitem":12,"minecraft:stone_pressure_plate":4,"minecraft:dark_oak_planks":14,"quark:netherrack_bricks":91,"minecraft:arrow":105,"pamhc2crops:jicamaitem":5,"pamhc2crops:bellpepperitem":2,"minecraft:saddle":2,"byg:rocky_stone":268,"minecraft:skeleton_skull":1,"pamhc2crops:cottonitem":1,"minecraft:jungle_boat":28,"artifacts:novelty_drinking_hat":1,"minecraft:salmon":118,"minecraft:leather":17,"pamhc2crops:barleyitem":3,"pamhc2crops:blueberryitem":1,"minecraft:ice":2,"pamhc2foodcore:bakedvegetablemedlyitem":5,"quark:diorite_bricks":1,"minecraft:chainmail_chestplate":1,"minecraft:gunpowder":17,"minecraft:cobblestone_wall":11,"minecraft:cobblestone_stairs":24,"pamhc2trees:walnutitem":1,"byg:firecracker_flower_bush":2,"byg:scoria_cobblestone":98,"byg:soapstone_tile":12,"artifacts:whoopee_cushion":1,"minecraft:iron_ingot":9,"quark:tallow":7,"minecraft:acacia_sapling":4,"pamhc2trees:hazelnutitem":1,"minecraft:book":59,"pamhc2crops:onionitem":1,"minecraft:scaffolding":126,"minecraft:oak_slab":4,"minecraft:emerald_block":1,"minecraft:pumpkin":13,"minecraft:dandelion":4,"minecraft:soul_torch":1,"minecraft:white_bed":4,"minecraft:gold_ore":35,"quark:oak_chest":3,"minecraft:spruce_door":3,"pamhc2trees:guavaitem":6,"minecraft:coal":618,"quark:white_candle":10},"minecraft:used":{"quark:bamboo_block":1,"minecraft:dispenser":2,"quark:cobblestone_bricks_slab":103,"minecraft:spruce_slab":7,"minecraft:poppy":1,"minecraft:ladder":12,"quark:bamboo_mat":2,"minecraft:chest":3,"pamhc2foodcore:friesitem":1,"byg:pine_planks":1,"pamhc2crops:tomatilloitem":1,"pamhc2crops:brusselsproutitem":1,"minecraft:rotten_flesh":4,"minecraft:cocoa_beans":3,"minecraft:acacia_sapling":1,"quark:stone_speleothem":10,"quark:jungle_trapped_chest":3,"minecraft:snowball":1,"pamhc2foodextended:chocolatecoconutbaritem":4,"minecraft:lava_bucket":2,"minecraft:music_disc_pigstep":3,"minecraft:jungle_fence_gate":2,"minecraft:grass_block":118,"minecraft:music_disc_ward":2,"minecraft:dark_oak_slab":5,"minecraft:bow":18,"minecraft:sweet_berries":3,"minecraft:oak_sapling":2,"minecraft:furnace":1,"minecraft:cooked_cod":1,"minecraft:egg":49,"minecraft:potato":1,"minecraft:diorite":3,"minecraft:spruce_door":6,"minecraft:cactus":1,"minecraft:composter":2,"byg:polished_soapstone":87,"pamhc2foodcore:friedeggitem":2,"minecraft:jungle_boat":31,"minecraft:oak_leaves":10,"minecraft:cookie":5,"minecraft:sand":2,"quark:cobblestone_bricks_wall":61,"minecraft:lectern":2,"quark:jasper":1,"minecraft:oak_pressure_plate":1,"quark:netherrack_bricks_stairs":46,"minecraft:soul_lantern":2,"minecraft:coal_block":3,"minecraft:smithing_table":2,"byg:soapstone_pillar":38,"quark:diorite_bricks_wall":6,"minecraft:iron_bars":1,"minecraft:enchanting_table":1,"minecraft:cooked_salmon":50,"pamhc2trees:coconutitem":7,"minecraft:torch":603,"minecraft:polished_diorite":21,"minecraft:iron_block":1,"minecraft:iron_axe":756,"pamhc2foodextended:bamboosteamedriceitem":63,"minecraft:jungle_log":1,"minecraft:melon_seeds":1,"minecraft:barrel":1,"minecraft:bamboo":9,"quark:dirt_bricks":4,"minecraft:iron_trapdoor":2,"pamhc2foodcore:basicfishsandwichitem":1,"quark:white_candle":31,"minecraft:wheat_seeds":500,"pamhc2trees:mangoitem":4,"minecraft:water_bucket":122,"quark:netherrack_bricks_wall":4,"quark:cobblestone_bricks":592,"pamhc2foodextended:blueberryjuiceitem":1,"minecraft:cauldron":1,"byg:rocky_stone":187,"minecraft:spruce_fence_gate":5,"pamhc2trees:plumitem":9,"minecraft:salmon":5,"minecraft:mossy_cobblestone":3,"minecraft:diamond_block":3,"minecraft:lime_terracotta":5,"minecraft:vine":6,"minecraft:crafting_table":14,"minecraft:campfire":2,"minecraft:white_bed":6,"pamhc2trees:orangeitem":2,"minecraft:diamond_pickaxe":4645,"minecraft:diamond_shovel":1840,"minecraft:iron_pickaxe":191,"minecraft:spruce_trapdoor":2,"pamhc2foodextended:hazelnutchocolateitem":1,"minecraft:cobblestone":1376,"quark:dark_oak_chest":3,"travelersbackpack:standard":22,"pamhc2crops:okraitem":2,"byg:scoria_cobblestone":31,"minecraft:glass_pane":36,"quark:oak_chest":3,"pamhc2trees:paperbark_sapling":1,"quark:magma_bricks":30,"pamhc2trees:candlenutitem":18,"minecraft:iron_shovel":248,"minecraft:melon":21,"pamhc2trees:pearitem":1,"minecraft:diamond_hoe":234,"minecraft:shield":64,"minecraft:iron_sword":58,"pamhc2crops:wintersquashitem":6,"pamhc2foodcore:mashedpotatoesitem":2,"minecraft:jungle_planks":139,"pamhc2trees:tamarinditem":1,"minecraft:milk_bucket":1,"minecraft:obsidian":4,"minecraft:glass":154,"byg:soapstone_tile":70,"quark:cobblestone_bricks_vertical_slab":60,"minecraft:lantern":1,"pamhc2crops:greengrapeitem":4,"pamhc2crops:blueberryitem":1,"minecraft:item_frame":1,"minecraft:golden_sword":4,"pamhc2foodextended:chocolatecherryitem":1,"minecraft:repeater":7,"minecraft:magma_block":2,"minecraft:scaffolding":162,"minecraft:hay_block":3,"minecraft:written_book":1,"minecraft:beetroot_seeds":4,"minecraft:gold_block":3,"minecraft:skeleton_skull":1,"pamhc2trees:pampaperbark":3,"pamhc2trees:cherryitem":3,"minecraft:stone_pickaxe":296,"minecraft:jungle_fence":89,"pamhc2crops:asparagusitem":1,"minecraft:redstone_block":5,"minecraft:sugar_cane":21,"minecraft:diamond_axe":471,"pamhc2trees:peachitem":1,"minecraft:crossbow":82,"minecraft:black_bed":4,"pamhc2crops:jicamaitem":1,"minecraft:shears":235,"quark:netherrack_bricks":629,"minecraft:lever":7,"minecraft:melon_slice":10,"minecraft:bread":4,"minecraft:string":4,"quark:cobblestone_bricks_stairs":273,"minecraft:gravel":177,"minecraft:grindstone":1,"minecraft:andesite":40,"minecraft:chain":14,"minecraft:coarse_dirt":1,"minecraft:bone_meal":10,"minecraft:jungle_leaves":1,"byg:firecracker_flower_bush":2,"minecraft:flint_and_steel":21,"minecraft:stone_shovel":676,"minecraft:redstone":27,"quark:vertical_jungle_planks":107,"quark:jungle_chest":7,"minecraft:spruce_planks":8,"quark:stone_vertical_slab":38,"minecraft:dirt":519,"minecraft:hopper":1,"minecraft:spruce_stairs":1,"minecraft:cobblestone_wall":42,"pamhc2foodextended:greengrapejellysandwichitem":13,"quark:framed_glass":4,"minecraft:granite":3,"minecraft:spruce_fence":5,"pamhc2trees:avocadoitem":4,"minecraft:dark_oak_planks":1,"quark:jungle_bookshelf":34,"pamhc2crops:onionitem":1,"minecraft:light_gray_wool":2,"minecraft:emerald_block":3,"minecraft:stone_pressure_plate":6,"minecraft:cooked_beef":13,"byg:rocky_stone_wall":8,"pamhc2foodextended:chocolateorangeitem":2,"minecraft:cobblestone_stairs":24,"minecraft:snow_block":4,"pamhc2foodextended:blueberrypieitem":2,"minecraft:baked_potato":1,"minecraft:andesite_slab":1,"minecraft:brown_mushroom":1,"minecraft:stonecutter":11,"minecraft:cobblestone_slab":56,"pamhc2foodcore:fishsticksitem":2,"minecraft:music_disc_cat":3,"quark:acacia_chest":1,"pamhc2trees:hazelnutitem":1,"minecraft:painting":30,"quark:cobblestone_vertical_slab":14,"minecraft:smoker":2,"pamhc2foodcore:fishjerkyitem":1,"quark:lime_framed_glass":34,"minecraft:apple":3,"pamhc2foodcore:bakedvegetablemedlyitem":12,"quark:oak_hedge":18,"minecraft:jungle_stairs":6,"pamhc2foodextended:melonjellysandwichitem":1,"quark:magma_bricks_stairs":3,"byg:soapstone":54,"minecraft:stone_axe":1247,"minecraft:fishing_rod":1,"endrem:end_castle_disc":2,"quark:diorite_bricks":15,"minecraft:white_banner":1,"minecraft:bucket":143,"minecraft:lapis_block":2,"minecraft:soul_torch":14},"minecraft:dropped":{"minecraft:cookie":4,"minecraft:bone_meal":1,"minecraft:salmon":1,"byg:rocky_stone":1,"minecraft:wheat_seeds":5,"pamhc2crops:wintersquashitem":1,"minecraft:cooked_salmon":1,"minecraft:diamond_pickaxe":1,"pamhc2trees:cherryitem":1,"travelersbackpack:standard":2,"minecraft:flint":1,"quark:jungle_chest":4,"minecraft:water_bucket":1,"minecraft:grass_block":52,"minecraft:melon_slice":1,"minecraft:iron_axe":1,"minecraft:bucket":2,"minecraft:shield":1},"minecraft:broken":{"minecraft:diamond_helmet":1,"minecraft:shears":1,"minecraft:golden_sword":1,"minecraft:diamond_leggings":1,"minecraft:shield":1,"minecraft:iron_axe":4,"minecraft:iron_shovel":1,"minecraft:stone_pickaxe":3,"minecraft:stone_axe":10,"minecraft:stone_shovel":5},"minecraft:killed":{"minecraft:skeleton":15,"minecraft:chicken":15,"minecraft:magma_cube":62,"minecraft:salmon":117,"minecraft:pillager":6,"minecraft:zombie":37,"minecraft:cow":9,"minecraft:husk":5,"minecraft:wandering_trader":1,"minecraft:zombified_piglin":36,"minecraft:witch":2,"minecraft:spider":4,"artifacts:mimic":1,"minecraft:piglin":1,"minecraft:pig":4,"minecraft:creeper":8,"minecraft:ghast":8,"minecraft:phantom":3,"minecraft:drowned":1,"minecraft:squid":2},"minecraft:crafted":{"minecraft:smooth_stone":3,"minecraft:jungle_fence_gate":2,"minecraft:melon":7,"quark:cobblestone_bricks_slab":98,"minecraft:chain":12,"quark:magma_bricks":52,"minecraft:diamond_shovel":2,"minecraft:lever":1,"quark:cactus_paste":1,"byg:soapstone_pillar":46,"minecraft:glass":182,"minecraft:repeater":2,"quark:netherrack_bricks":656,"minecraft:stone_pressure_plate":2,"quark:cobblestone_vertical_slab":44,"minecraft:emerald":157,"minecraft:diamond_axe":1,"minecraft:jungle_boat":6,"quark:jungle_bookshelf":21,"travelersbackpack:standard":2,"minecraft:spruce_door":6,"minecraft:clock":1,"minecraft:hay_block":36,"minecraft:campfire":2,"minecraft:painting":8,"minecraft:compass":1,"minecraft:iron_pickaxe":1,"minecraft:iron_block":1,"minecraft:gold_ingot":54,"minecraft:spruce_fence_gate":5,"minecraft:stone_shovel":5,"minecraft:leather_leggings":10,"minecraft:iron_nugget":36,"minecraft:diamond_hoe":4,"quark:jungle_chest":11,"minecraft:bone_meal":9,"minecraft:spruce_fence":3,"quark:lime_framed_glass":16,"pamhc2trees:paperbark_sapling":1,"quark:diorite_bricks":24,"minecraft:lantern":1,"minecraft:polished_diorite":20,"minecraft:ladder":12,"quark:cobblestone_bricks":1108,"minecraft:spruce_slab":6,"minecraft:stone_pickaxe":2,"minecraft:redstone_block":1,"minecraft:jungle_fence":48,"quark:spruce_chest":1,"minecraft:dark_oak_planks":4,"quark:cobblestone_bricks_stairs":54,"quark:spruce_trapped_chest":1,"minecraft:wheat":396,"quark:cobblestone_bricks_wall":42,"minecraft:soul_lantern":1,"pamhc2foodcore:freshwateritem":8,"quark:bamboo_mat":2,"minecraft:iron_shovel":2,"minecraft:iron_leggings":1,"minecraft:white_bed":3,"byg:polished_soapstone":28,"minecraft:cobblestone_slab":48,"minecraft:barrel":1,"quark:bamboo_block":1,"travelersbackpack:sleeping_bag":2,"minecraft:stone":19,"byg:pine_planks":84,"minecraft:green_dye":1,"minecraft:hopper":1,"minecraft:bow":3,"minecraft:iron_boots":1,"minecraft:jungle_stairs":8,"quark:dirt_bricks":4,"minecraft:smoker":1,"minecraft:dropper":1,"minecraft:oak_slab":6,"minecraft:item_frame":1,"minecraft:arrow":212,"minecraft:cauldron":1,"minecraft:crafting_table":10,"minecraft:spruce_planks":60,"minecraft:iron_helmet":1,"quark:vertical_jungle_planks":213,"quark:white_candle":28,"minecraft:red_wool":4,"quark:oak_hedge":18,"minecraft:gold_block":1,"minecraft:dispenser":1,"minecraft:spruce_trapdoor":2,"quark:jungle_trapped_chest":3,"minecraft:dark_oak_slab":6,"minecraft:iron_chestplate":1,"minecraft:paper":15,"minecraft:diamond_pickaxe":1,"minecraft:shield":2,"minecraft:stick":440,"minecraft:iron_ingot":336,"minecraft:snow_block":4,"quark:cobblestone_bricks_vertical_slab":12,"minecraft:redstone_torch":4,"minecraft:shears":1,"minecraft:cookie":24,"minecraft:redstone":9,"minecraft:coal":720,"minecraft:tripwire_hook":2,"minecraft:furnace":2,"quark:framed_glass":20,"minecraft:glass_pane":32,"minecraft:flint_and_steel":1,"minecraft:scaffolding":48,"quark:acacia_chest":4,"minecraft:iron_axe":4,"minecraft:lime_dye":2,"minecraft:cobblestone_wall":12,"minecraft:filled_map":1,"pamhc2foodcore:friedeggitem":2,"minecraft:cooked_beef":14,"minecraft:red_dye":4,"minecraft:iron_trapdoor":2,"travelersbackpack:backpack_tank":4,"minecraft:bucket":1,"minecraft:stone_axe":9,"minecraft:air":0,"minecraft:jungle_planks":736,"minecraft:white_wool":1,"quark:diorite_bricks_wall":6,"minecraft:white_dye":1,"minecraft:acacia_planks":32,"minecraft:torch":436,"minecraft:lapis_block":1},"minecraft:killed_by":{"minecraft:skeleton":1},"minecraft:custom":{"minecraft:interact_with_crafting_table":224,"minecraft:open_barrel":55,"minecraft:bell_ring":1,"minecraft:leave_game":41,"minecraft:time_since_death":992851,"minecraft:damage_blocked_by_shield":2310,"minecraft:deaths":1,"minecraft:jump":12728,"minecraft:enchant_item":2,"minecraft:interact_with_furnace":191,"minecraft:play_record":10,"minecraft:traded_with_villager":186,"minecraft:interact_with_cartography_table":1,"minecraft:sleep_in_bed":48,"minecraft:damage_dealt":26564,"minecraft:interact_with_smoker":14,"minecraft:inspect_dispenser":16,"minecraft:horse_one_cm":6530476,"minecraft:interact_with_smithing_table":5,"minecraft:inspect_hopper":4,"minecraft:sneak_time":95912,"minecraft:interact_with_lectern":2,"minecraft:interact_with_blast_furnace":80,"minecraft:tune_noteblock":23,"minecraft:interact_with_stonecutter":51,"minecraft:time_since_rest":10077,"minecraft:swim_one_cm":86681,"minecraft:fly_one_cm":3127769,"minecraft:open_chest":1324,"minecraft:fish_caught":1,"minecraft:fall_one_cm":238117,"minecraft:animals_bred":46,"minecraft:sprint_one_cm":3349650,"minecraft:drop":81,"minecraft:talked_to_villager":129,"minecraft:interact_with_brewingstand":1,"minecraft:walk_on_water_one_cm":440244,"minecraft:play_one_minute":1928754,"minecraft:open_enderchest":9,"minecraft:crouch_one_cm":286242,"minecraft:mob_kills":341,"minecraft:interact_with_campfire":51,"minecraft:damage_dealt_resisted":714,"minecraft:climb_one_cm":265993,"minecraft:walk_one_cm":7882399,"minecraft:walk_under_water_one_cm":240574,"minecraft:boat_one_cm":1993148,"minecraft:interact_with_grindstone":4,"minecraft:damage_taken":11010,"minecraft:trigger_trapped_chest":17}},"DataVersion":2586}